constantQ/__init__.py
constantQ/frequencyseries.py
constantQ/index.py
constantQ/mp.py
constantQ/qtransform.py
constantQ/segments.py
constantQ/series.py
constantQ/spectrogram.py
constantQ/timeseries.py
constantQ/utilityaccess.py
constantQ/spectral/__init__.py
constantQ/spectral/_lal.py
constantQ/spectral/_registry.py
constantQ/spectral/_scipy.py
constantQ/spectral/_ui.py
constantQ/spectral/_utils.py
constantQ-0.0.1.dist-info/LICENSE.txt
constantQ-0.0.1.dist-info/METADATA
constantQ-0.0.1.dist-info/WHEEL
constantQ-0.0.1.dist-info/top_level.txt
constantQ-0.0.1.dist-info/RECORD
