Metadata-Version: 2.1
Name: constantQ
Version: 0.0.1
Summary: constantQ: Constant Q Transform with minimal size and dependencies based on GWpy qtransform.
Home-page: https://xli2522.github.io/Constant-Q/
Author: Xiyuan Li
Author-email: xli2522@uwo.ca
License: GNU
Platform: UNKNOWN
Classifier: Natural Language :: English
Classifier: Programming Language :: Python :: 3
Classifier: License :: OSI Approved :: GNU General Public License v3 (GPLv3)
Classifier: Operating System :: OS Independent
Requires-Python: >=3.6
